cli_calc/__init__.py
cli_calc/__main__.py
cli_calc/arg_parser.py
cli_calc/cli_eval.py
cli_calc/cli_output.py
cli_calc/config.py
cli_calc/constant.py
cli_calc/format.py
cli_calc/ieee.py
cli_calc/input.py
cli_calc/input_cli.py
cli_calc/input_from_pipe.py
cli_calc/memory.py
cli_calc/py.typed
cli_calc/read_line_parser.py
cli_calc-0.3.8.dist-info/LICENSE
cli_calc-0.3.8.dist-info/WHEEL
cli_calc-0.3.8.dist-info/METADATA
cli_calc-0.3.8.dist-info/RECORD
