Metadata-Version: 2.1
Name: cli-calc
Version: 0.3.8
Summary: Powerful yet easy command line calculator.
Home-page: https://github.com/cruisen/cli-calc
License: MIT
Keywords: calculator,math,cli,command line,console,python
Author: Nikolai von Krusenstiern
Requires-Python: >=3.8,<4.0
Classifier: Development Status :: 4 - Beta
Classifier: Environment :: Console
Classifier: Intended Audience :: End Users/Desktop
Classifier: Intended Audience :: Science/Research
Classifier: License :: OSI Approved :: MIT License
Classifier: Natural Language :: English
Classifier: Operating System :: OS Independent
Classifier: Programming Language :: Python :: 3
Classifier: Programming Language :: Python :: 3.10
Classifier: Programming Language :: Python :: 3.8
Classifier: Programming Language :: Python :: 3.9
Classifier: Topic :: Scientific/Engineering :: Mathematics
Classifier: Topic :: Software Development :: Libraries :: Python Modules
Classifier: Topic :: Utilities
Requires-Dist: ConfigArgParse (>=1.5.3,<2.0.0)
Requires-Dist: python-git-wrapper (>=0.9.0,<0.10.0)
Project-URL: Repository, https://github.com/cruisen/cli-calc
